chartart/__init__.py
chartart/conftest.py
chartart/dashboardVisualiser.py
chartart/helpers.py
chartart/pdfExporter.py
chartart/plot.py
chartart/simple_eda_template.py
chartart/test_plot.py
chartart/tests/__init__.py
chartart/tests/test_simple.py
chartart-0.0.3.dev44.dist-info/licenses/LICENSE
chartart-0.0.3.dev44.dist-info/METADATA
chartart-0.0.3.dev44.dist-info/WHEEL
chartart-0.0.3.dev44.dist-info/top_level.txt
chartart-0.0.3.dev44.dist-info/RECORD
