Metadata-Version: 2.4
Name: chartart
Version: 0.0.3.dev44
Summary: ChartArt python package
Home-page: https://github.com/pypa/sampleproject
Author: BR-Advisers
Author-email: info@br-advisers.com
Project-URL: Bug Tracker, https://github.com/pypa/sampleproject/issues
Keywords: chartart,NLP
Classifier: Programming Language :: Python :: 3
Classifier: License :: OSI Approved :: MIT License
Classifier: Operating System :: OS Independent
Requires-Python: >=3.6
License-File: LICENSE
Requires-Dist: pandas
Requires-Dist: numpy
Requires-Dist: ipython
Requires-Dist: ipykernel
Requires-Dist: ipynbname
Requires-Dist: matplotlib
Dynamic: license-file
